[
    {
        "Mode":  "common",
        "Enabled":  "false",
        "BorderRadius":  "0.475rem",
        "FontFamily":  "\u0027Inter\u0027, sans-serif",
        "Black":  "#535178",
        "White":  "#ffffff",
        "Yellow":  "#fdd877",
        "YellowRGBA15":  "#26fdd877",
        "YellowARGB15":  "#fdd87726",
        "YellowARGB95":  "#fdd877F2",
        "YellowHover":  "#d89c04",
        "Red":  "#ef6487",
        "RedRGBA15":  "#26ef6487",
        "RedARGB15":  "#ef648726",
        "RedARGB95":  "#ef6487F2",
        "RedHover":  "#bb143e",
        "Green":  "#5eca89",
        "GreenRGBA15":  "#265eca89",
        "GreenARGB15":  "#5eca8926",
        "GreenARGB95":  "#5eca89F2",
        "GreenHover":  "#297b4a",
        "Blue":  "#65aef7",
        "BlueRGBA15":  "#2665aef7",
        "BlueARGB15":  "#65aef726",
        "BlueARGB95":  "#65aef7F2",
        "BlueHover":  "#0b6bcc",
        "Purple":  "#aa7ff0",
        "PurpleRGBA15":  "#26aa7ff0",
        "PurpleARGB15":  "#aa7ff026",
        "PurpleARGB95":  "#aa7ff0F2",
        "PurpleHover":  "#6018d3",
        "Cyan":  "#43c1be",
        "CyanRGBA15":  "#2643c1be",
        "CyanARGB15":  "#43c1be26",
        "CyanARGB95":  "#43c1beF2",
        "CyanHover":  "#20605f"
    },
    {
        "Mode":  "dark",
        "Enabled":  "true",
        "Main":  "#000000",
        "MainSecondary":  "#29283b",
        "MainGamma":  "#595883",
        "MainDelta":  "#6a6899",
        "OppositeSecondary":  "#a5a77c",
        "Opposite":  "#a4a67c",
        "HighContrast":  "#D6D7C4"
    },
    {
        "Mode":  "light",
        "Enabled":  "true",
        "Main":  "#FFFFFF",
        "MainSecondary":  "#D6D7C4",
        "MainGamma":  "#A6A77C",
        "MainDelta":  "#959766",
        "OppositeSecondary":  "#5A5883",
        "Opposite":  "#5B5983",
        "HighContrast":  "#29283b"
    }
]
