[
    {
        "Mode":  "common",
        "Enabled":  "false",
        "BorderRadius":  "0.475rem",
        "FontFamily":  "\u0027Inter\u0027, sans-serif",
        "Black":  "#000000",
        "White":  "#f7f7f7",
        "Yellow":  "#cb9000",
        "YellowRGBA15":  "#26cb9000",
        "YellowARGB15":  "#cb900026",
        "YellowARGB95":  "#cb9000F2",
        "YellowHover":  "#4b3600",
        "Red":  "#aa3731",
        "RedRGBA15":  "#26aa3731",
        "RedARGB15":  "#aa373126",
        "RedARGB95":  "#aa3731F2",
        "RedHover":  "#471714",
        "Green":  "#448c27",
        "GreenRGBA15":  "#26448c27",
        "GreenARGB15":  "#448c2726",
        "GreenARGB95":  "#448c27F2",
        "GreenHover":  "#13280b",
        "Blue":  "#325cc0",
        "BlueRGBA15":  "#26325cc0",
        "BlueARGB15":  "#325cc026",
        "BlueARGB95":  "#325cc0F2",
        "BlueHover":  "#182c5b",
        "Purple":  "#7a3e9d",
        "PurpleRGBA15":  "#267a3e9d",
        "PurpleARGB15":  "#7a3e9d26",
        "PurpleARGB95":  "#7a3e9dF2",
        "PurpleHover":  "#331a41",
        "Cyan":  "#0083b2",
        "CyanRGBA15":  "#260083b2",
        "CyanARGB15":  "#0083b226",
        "CyanARGB95":  "#0083b2F2",
        "CyanHover":  "#002532"
    },
    {
        "Mode":  "light",
        "Enabled":  "true",
        "Main":  "#fdfdfd",
        "MainSecondary":  "#f7f7f7",
        "MainGamma":  "#787878",
        "MainDelta":  "#5e5e5e",
        "OppositeSecondary":  "#2b2b2b",
        "Opposite":  "#121212",
        "HighContrast":  "#080808"
    },
    {
        "Mode":  "dark",
        "Enabled":  "true",
        "Main":  "#020202",
        "MainSecondary":  "#080808",
        "MainGamma":  "#878787",
        "MainDelta":  "#A1A1A1",
        "OppositeSecondary":  "#D4D4D4",
        "Opposite":  "#EDEDED",
        "HighContrast":  "#f7f7f7"
    }
]
