[
    {
        "Mode":  "common",
        "Enabled":  "false",
        "BorderRadius":  "0.475rem",
        "FontFamily":  "\u0027Inter\u0027, sans-serif",
        "Black":  "#000000",
        "White":  "#bbbbbb",
        "Yellow":  "#bbbb00",
        "YellowRGBA15":  "#26bbbb00",
        "YellowARGB15":  "#bbbb0026",
        "YellowARGB95":  "#bbbb00F2",
        "YellowHover":  "#3c3c00",
        "Red":  "#bb0000",
        "RedRGBA15":  "#26bb0000",
        "RedARGB15":  "#bb000026",
        "RedARGB95":  "#bb0000F2",
        "RedHover":  "#3c0000",
        "Green":  "#00bb00",
        "GreenRGBA15":  "#2600bb00",
        "GreenARGB15":  "#00bb0026",
        "GreenARGB95":  "#00bb00F2",
        "GreenHover":  "#003c00",
        "Blue":  "#0000bb",
        "BlueRGBA15":  "#260000bb",
        "BlueARGB15":  "#0000bb26",
        "BlueARGB95":  "#0000bbF2",
        "BlueHover":  "#00003c",
        "Purple":  "#bb00bb",
        "PurpleRGBA15":  "#26bb00bb",
        "PurpleARGB15":  "#bb00bb26",
        "PurpleARGB95":  "#bb00bbF2",
        "PurpleHover":  "#3c003c",
        "Cyan":  "#00bbbb",
        "CyanRGBA15":  "#2600bbbb",
        "CyanARGB15":  "#00bbbb26",
        "CyanARGB95":  "#00bbbbF2",
        "CyanHover":  "#003c3c"
    },
    {
        "Mode":  "dark",
        "Enabled":  "true",
        "Main":  "#000000",
        "MainSecondary":  "#000000",
        "MainGamma":  "#848484",
        "MainDelta":  "#c4c4c4",
        "OppositeSecondary":  "#ebebeb",
        "Opposite":  "#e6e6e6",
        "HighContrast":  "#FFFFFF"
    },
    {
        "Mode":  "light",
        "Enabled":  "true",
        "Main":  "#ffffff",
        "MainSecondary":  "#ffffff",
        "MainGamma":  "#808080",
        "MainDelta":  "#666666",
        "OppositeSecondary":  "#333333",
        "Opposite":  "#1a1a1a",
        "HighContrast":  "#000000"
    }
]
