[
    {
        "Mode":  "common",
        "Enabled":  "false",
        "BorderRadius":  "0.475rem",
        "FontFamily":  "\u0027Inter\u0027, sans-serif",
        "Black":  "#1e1e1e",
        "White":  "#ffffff",
        "Yellow":  "#ffd60a",
        "YellowRGBA15":  "#26ffd60a",
        "YellowARGB15":  "#ffd60a26",
        "YellowARGB95":  "#ffd60aF2",
        "YellowHover":  "#8a7300",
        "Red":  "#ff453a",
        "RedRGBA15":  "#26ff453a",
        "RedARGB15":  "#ff453a26",
        "RedARGB95":  "#ff453aF2",
        "RedHover":  "#ba0900",
        "Green":  "#32d74b",
        "GreenRGBA15":  "#2632d74b",
        "GreenARGB15":  "#32d74b26",
        "GreenARGB95":  "#32d74bF2",
        "GreenHover":  "#177324",
        "Blue":  "#0a84ff",
        "BlueRGBA15":  "#260a84ff",
        "BlueARGB15":  "#0a84ff26",
        "BlueARGB95":  "#0a84ffF2",
        "BlueHover":  "#00458a",
        "Purple":  "#bf5af2",
        "PurpleRGBA15":  "#26bf5af2",
        "PurpleARGB15":  "#bf5af226",
        "PurpleARGB95":  "#bf5af2F2",
        "PurpleHover":  "#830fbe",
        "Cyan":  "#5ac8fa",
        "CyanRGBA15":  "#265ac8fa",
        "CyanARGB15":  "#5ac8fa26",
        "CyanARGB95":  "#5ac8faF2",
        "CyanHover":  "#068fce"
    },
    {
        "Mode":  "dark",
        "Enabled":  "true",
        "Main":  "#161616",
        "MainSecondary":  "#1e1e1e",
        "MainGamma":  "#929292",
        "MainDelta":  "#d2d2d2",
        "OppositeSecondary":  "#cdcdcd",
        "Opposite":  "#c7c7c7",
        "HighContrast":  "#E1E1E1"
    }
]
