[
    {
        "Mode":  "common",
        "Enabled":  "false",
        "BorderRadius":  "0.475rem",
        "FontFamily":  "\u0027Inter\u0027, sans-serif",
        "Black":  "#403e41",
        "White":  "#fcfcfa",
        "Yellow":  "#ffd866",
        "YellowRGBA15":  "#26ffd866",
        "YellowARGB15":  "#ffd86626",
        "YellowARGB95":  "#ffd866F2",
        "YellowHover":  "#d29e00",
        "Red":  "#ff6188",
        "RedRGBA15":  "#26ff6188",
        "RedARGB15":  "#ff618826",
        "RedARGB95":  "#ff6188F2",
        "RedHover":  "#cc0033",
        "Green":  "#a9dc76",
        "GreenRGBA15":  "#26a9dc76",
        "GreenARGB15":  "#a9dc7626",
        "GreenARGB95":  "#a9dc76F2",
        "GreenHover":  "#67a42a",
        "Blue":  "#fc9867",
        "BlueRGBA15":  "#26fc9867",
        "BlueARGB15":  "#fc986726",
        "BlueARGB95":  "#fc9867F2",
        "BlueHover":  "#da4b04",
        "Purple":  "#ab9df2",
        "PurpleRGBA15":  "#26ab9df2",
        "PurpleARGB15":  "#ab9df226",
        "PurpleARGB95":  "#ab9df2F2",
        "PurpleHover":  "#4627e2",
        "Cyan":  "#78dce8",
        "CyanRGBA15":  "#2678dce8",
        "CyanARGB15":  "#78dce826",
        "CyanARGB95":  "#78dce8F2",
        "CyanHover":  "#1fa8b7"
    },
    {
        "Mode":  "dark",
        "Enabled":  "true",
        "Main":  "#0b0b0b",
        "MainSecondary":  "#403e41",
        "MainGamma":  "#7b6d7e",
        "MainDelta":  "#908c91",
        "OppositeSecondary":  "#879285",
        "Opposite":  "#898f88",
        "HighContrast":  "#BFC1BE"
    },
    {
        "Mode":  "light",
        "Enabled":  "true",
        "Main":  "#F4F4F4",
        "MainSecondary":  "#BFC1BE",
        "MainGamma":  "#849281",
        "MainDelta":  "#6F736E",
        "OppositeSecondary":  "#786D7A",
        "Opposite":  "#767077",
        "HighContrast":  "#403e41"
    }
]
