[
    {
        "Mode":  "common",
        "Enabled":  "false",
        "BorderRadius":  "0.475rem",
        "FontFamily":  "\u0027Inter\u0027, sans-serif",
        "Black":  "#1b1d1e",
        "White":  "#d9d8d1",
        "Yellow":  "#63e457",
        "YellowRGBA15":  "#2663e457",
        "YellowARGB15":  "#63e45726",
        "YellowARGB95":  "#63e457F2",
        "YellowHover":  "#25a21a",
        "Red":  "#269d1b",
        "RedRGBA15":  "#26269d1b",
        "RedARGB15":  "#269d1b26",
        "RedARGB95":  "#269d1bF2",
        "RedHover":  "#0c3008",
        "Green":  "#13ce30",
        "GreenRGBA15":  "#2613ce30",
        "GreenARGB15":  "#13ce3026",
        "GreenARGB95":  "#13ce30F2",
        "GreenHover":  "#085914",
        "Blue":  "#2525f5",
        "BlueRGBA15":  "#262525f5",
        "BlueARGB15":  "#2525f526",
        "BlueARGB95":  "#2525f5F2",
        "BlueHover":  "#070794",
        "Purple":  "#641f74",
        "PurpleRGBA15":  "#26641f74",
        "PurpleARGB15":  "#641f7426",
        "PurpleARGB95":  "#641f74F2",
        "PurpleHover":  "#0d040f",
        "Cyan":  "#378ca9",
        "CyanRGBA15":  "#26378ca9",
        "CyanARGB15":  "#378ca926",
        "CyanARGB95":  "#378ca9F2",
        "CyanHover":  "#183c49"
    },
    {
        "Mode":  "dark",
        "Enabled":  "true",
        "Main":  "#141516",
        "MainSecondary":  "#1b1d1e",
        "MainGamma":  "#909292",
        "MainDelta":  "#d0d1d1",
        "OppositeSecondary":  "#d1cdcb",
        "Opposite":  "#ccc8c6",
        "HighContrast":  "#E4E2E1"
    },
    {
        "Mode":  "light",
        "Enabled":  "true",
        "Main":  "#EBEAE9",
        "MainSecondary":  "#E4E2E1",
        "MainGamma":  "#6F6D6D",
        "MainDelta":  "#2F2E2E",
        "OppositeSecondary":  "#2E3234",
        "Opposite":  "#333739",
        "HighContrast":  "#1b1d1e"
    }
]
