[
    {
        "Mode":  "common",
        "Enabled":  "false",
        "BorderRadius":  "0.475rem",
        "FontFamily":  "\u0027Inter\u0027, sans-serif",
        "Black":  "#000000",
        "White":  "#ffffff",
        "Yellow":  "#ffeead",
        "YellowRGBA15":  "#26ffeead",
        "YellowARGB15":  "#ffeead26",
        "YellowARGB95":  "#ffeeadF2",
        "YellowHover":  "#e1b400",
        "Red":  "#ff9da4",
        "RedRGBA15":  "#26ff9da4",
        "RedARGB15":  "#ff9da426",
        "RedARGB95":  "#ff9da4F2",
        "RedHover":  "#ff1928",
        "Green":  "#d1f1a9",
        "GreenRGBA15":  "#26d1f1a9",
        "GreenARGB15":  "#d1f1a926",
        "GreenARGB95":  "#d1f1a9F2",
        "GreenHover":  "#81cf23",
        "Blue":  "#bbdaff",
        "BlueRGBA15":  "#26bbdaff",
        "BlueARGB15":  "#bbdaff26",
        "BlueARGB95":  "#bbdaffF2",
        "BlueHover":  "#3791ff",
        "Purple":  "#ebbbff",
        "PurpleRGBA15":  "#26ebbbff",
        "PurpleARGB15":  "#ebbbff26",
        "PurpleARGB95":  "#ebbbffF2",
        "PurpleHover":  "#c337ff",
        "Cyan":  "#99ffff",
        "CyanRGBA15":  "#2699ffff",
        "CyanARGB15":  "#99ffff26",
        "CyanARGB95":  "#99ffffF2",
        "CyanHover":  "#00d3d3"
    },
    {
        "Mode":  "dark",
        "Enabled":  "true",
        "Main":  "#000000",
        "MainSecondary":  "#002451",
        "MainGamma":  "#0054bb",
        "MainDelta":  "#006cef",
        "OppositeSecondary":  "#fd8b00",
        "Opposite":  "#fd8b00",
        "HighContrast":  "#FFDBAE"
    },
    {
        "Mode":  "light",
        "Enabled":  "true",
        "Main":  "#FFFFFF",
        "MainSecondary":  "#FFDBAE",
        "MainGamma":  "#FFAB44",
        "MainDelta":  "#FF9310",
        "OppositeSecondary":  "#0274FF",
        "Opposite":  "#0274FF",
        "HighContrast":  "#002451"
    }
]
