[
    {
        "Mode":  "common",
        "Enabled":  "false",
        "BorderRadius":  "0.475rem",
        "FontFamily":  "\u0027Inter\u0027, sans-serif",
        "Black":  "#141414",
        "White":  "#ffffd4",
        "Yellow":  "#c2a86c",
        "YellowRGBA15":  "#26c2a86c",
        "YellowARGB15":  "#c2a86c26",
        "YellowARGB95":  "#c2a86cF2",
        "YellowHover":  "#7b6633",
        "Red":  "#c06d44",
        "RedRGBA15":  "#26c06d44",
        "RedARGB15":  "#c06d4426",
        "RedARGB95":  "#c06d44F2",
        "RedHover":  "#633721",
        "Green":  "#afb97a",
        "GreenRGBA15":  "#26afb97a",
        "GreenARGB15":  "#afb97a26",
        "GreenARGB95":  "#afb97aF2",
        "GreenHover":  "#6c763e",
        "Blue":  "#44474a",
        "BlueRGBA15":  "#2644474a",
        "BlueARGB15":  "#44474a26",
        "BlueARGB95":  "#44474aF2",
        "BlueHover":  "#070707",
        "Purple":  "#b4be7c",
        "PurpleRGBA15":  "#26b4be7c",
        "PurpleARGB15":  "#b4be7c26",
        "PurpleARGB95":  "#b4be7cF2",
        "PurpleHover":  "#737d3e",
        "Cyan":  "#778385",
        "CyanRGBA15":  "#26778385",
        "CyanARGB15":  "#77838526",
        "CyanARGB95":  "#778385F2",
        "CyanHover":  "#3b4142"
    },
    {
        "Mode":  "dark",
        "Enabled":  "true",
        "Main":  "#0c0c0c",
        "MainSecondary":  "#141414",
        "MainGamma":  "#8c8c8c",
        "MainDelta":  "#cbcbcb",
        "OppositeSecondary":  "#d7d7d7",
        "Opposite":  "#d2d2d2",
        "HighContrast":  "#EBEBEB"
    },
    {
        "Mode":  "light",
        "Enabled":  "true",
        "Main":  "#F3F3F3",
        "MainSecondary":  "#EBEBEB",
        "MainGamma":  "#737373",
        "MainDelta":  "#343434",
        "OppositeSecondary":  "#282828",
        "Opposite":  "#2D2D2D",
        "HighContrast":  "#141414"
    }
]
